geojikuu_kainedusher/aggregation/point_aggregators.py
geojikuu_kainedusher/descriptives/spacetime_distribution.py
geojikuu_kainedusher/descriptives/spatial_distribution.py
geojikuu_kainedusher/hypothesis_testing/hot_spot_analysis.py
geojikuu_kainedusher/preprocessing/conversion_tools.py
geojikuu_kainedusher/preprocessing/normalisation.py
geojikuu_kainedusher/preprocessing/projection.py
geojikuu_kainedusher-0.23.34.dist-info/METADATA
geojikuu_kainedusher-0.23.34.dist-info/WHEEL
geojikuu_kainedusher-0.23.34.dist-info/licenses/LICENSE.txt
geojikuu_kainedusher-0.23.34.dist-info/RECORD
