Metadata-Version: 2.1
Name: geojikuu_kainedusher
Version: 0.23.34
Summary: GeoJikuu is a Python library for analysing geographical data that contains both spatial and spatiotemporal variables.
Project-URL: Homepage, https://github.com/kainedusher/GeoJikuu
Author-email: Kaine Usher <kaine.usher1@gmail.com>
License-File: LICENSE.txt
Classifier: License :: OSI Approved :: Apache Software License
Classifier: Operating System :: OS Independent
Classifier: Programming Language :: Python :: 3
Requires-Python: >=3.8
